[
  {
    "Version": "5.5.3-latest.20220602.2",
    "Architecture": "x64",
    "Release": "Alpha",
    "Date": "2022-06-02T20:23:02.854Z",
    "Size": 248430464,
    "Sha512": "AjzjoAdz+ylU9kSOnXpYLm+w/wKhu3bo75ABrctEkNkKpH64innb0MFDwa3YHelx1lo+3RcZV0IqKMFWVWiDgw==",
    "URI": "https://downloads.k8slens.dev/ide/Lens%20Setup%205.5.3-latest.20220602.2.exe"
  },
  {
    "Version": "5.5.3-latest.20220602.2",
    "Architecture": "x64",
    "Release": "Stable",
    "Date": "2022-06-02T20:23:02.854Z",
    "Size": 248430464,
    "Sha512": "AjzjoAdz+ylU9kSOnXpYLm+w/wKhu3bo75ABrctEkNkKpH64innb0MFDwa3YHelx1lo+3RcZV0IqKMFWVWiDgw==",
    "URI": "https://downloads.k8slens.dev/ide/Lens%20Setup%205.5.3-latest.20220602.2.exe"
  }
]