[
  {
    "Version": "1.12.3296.0",
    "Size": 18190336,
    "Hash": "5ae32ad9bd6d18704a0920fdb38e12fac4d88047",
    "Language": "en_US",
    "Architecture": "x64",
    "Type": "msi",
    "URI": "https://repository.eset.com/v1/com/eset/apps/business/eei/agent/v1/1.12.3296.0/ei_connector_nt64.msi"
  },
  {
    "Version": "1.12.3296.0",
    "Size": 16003072,
    "Hash": "27ca48b54e01df48784ca5f2e80af28d73b9d6ff",
    "Language": "en_US",
    "Architecture": "x86",
    "Type": "msi",
    "URI": "https://repository.eset.com/v1/com/eset/apps/business/eei/agent/v1/1.12.3296.0/ei_connector_nt32.msi"
  }
]