[
  {
    "Version": "124.0.6367.0",
    "Revision": "1274542",
    "Channel": "Canary",
    "Architecture": "x64",
    "Type": "zip",
    "URI": "https://storage.googleapis.com/chrome-for-testing-public/124.0.6367.0/win64/chromedriver-win64.zip"
  },
  {
    "Version": "124.0.6367.0",
    "Revision": "1274542",
    "Channel": "Canary",
    "Architecture": "x86",
    "Type": "zip",
    "URI": "https://storage.googleapis.com/chrome-for-testing-public/124.0.6367.0/win32/chromedriver-win32.zip"
  },
  {
    "Version": "124.0.6356.2",
    "Revision": "1272107",
    "Channel": "Dev",
    "Architecture": "x64",
    "Type": "zip",
    "URI": "https://storage.googleapis.com/chrome-for-testing-public/124.0.6356.2/win64/chromedriver-win64.zip"
  },
  {
    "Version": "124.0.6356.2",
    "Revision": "1272107",
    "Channel": "Dev",
    "Architecture": "x86",
    "Type": "zip",
    "URI": "https://storage.googleapis.com/chrome-for-testing-public/124.0.6356.2/win32/chromedriver-win32.zip"
  },
  {
    "Version": "123.0.6312.46",
    "Revision": "1262506",
    "Channel": "Beta",
    "Architecture": "x64",
    "Type": "zip",
    "URI": "https://storage.googleapis.com/chrome-for-testing-public/123.0.6312.46/win64/chromedriver-win64.zip"
  },
  {
    "Version": "123.0.6312.46",
    "Revision": "1262506",
    "Channel": "Beta",
    "Architecture": "x86",
    "Type": "zip",
    "URI": "https://storage.googleapis.com/chrome-for-testing-public/123.0.6312.46/win32/chromedriver-win32.zip"
  },
  {
    "Version": "122.0.6261.128",
    "Revision": "1250580",
    "Channel": "Stable",
    "Architecture": "x64",
    "Type": "zip",
    "URI": "https://storage.googleapis.com/chrome-for-testing-public/122.0.6261.128/win64/chromedriver-win64.zip"
  },
  {
    "Version": "122.0.6261.128",
    "Revision": "1250580",
    "Channel": "Stable",
    "Architecture": "x86",
    "Type": "zip",
    "URI": "https://storage.googleapis.com/chrome-for-testing-public/122.0.6261.128/win32/chromedriver-win32.zip"
  }
]