[
  {
    "Version": "1.12.1",
    "Date": "15/12/2025",
    "Size": 93830808,
    "Sha256": "0f96d4209e408d54806146236344c738f93fcd286a72c3f94dbd84288411a06e",
    "Architecture": "x64",
    "InstallerType": "Default",
    "Type": "exe",
    "URI": "https://github.com/grafana/alloy/releases/download/v1.12.1/alloy-installer-windows-amd64.exe"
  },
  {
    "Version": "1.12.1",
    "Date": "15/12/2025",
    "Size": 88504818,
    "Sha256": "b946fbf0f54f3c3abdc251970832b84631d2ee9ce874047de83ee20eb58cf5dc",
    "Architecture": "x64",
    "InstallerType": "Default",
    "Type": "zip",
    "URI": "https://github.com/grafana/alloy/releases/download/v1.12.1/alloy-freebsd-amd64.zip"
  },
  {
    "Version": "1.12.1",
    "Date": "15/12/2025",
    "Size": 91326582,
    "Sha256": "2bda6205f2e6cfaae7d640a96d0da25d7b4efc4fefb7a66609ed1b4a10dfa393",
    "Architecture": "x64",
    "InstallerType": "Default",
    "Type": "zip",
    "URI": "https://github.com/grafana/alloy/releases/download/v1.12.1/alloy-installer-windows-amd64.exe.zip"
  },
  {
    "Version": "1.12.1",
    "Date": "15/12/2025",
    "Size": 93131167,
    "Sha256": "d30e8d95958429f59d349332ce458f54d3211c8a9a2318938df56757ca20c0e8",
    "Architecture": "x64",
    "InstallerType": "Default",
    "Type": "zip",
    "URI": "https://github.com/grafana/alloy/releases/download/v1.12.1/alloy-windows-amd64.exe.zip"
  }
]