[
  {
    "Version": "16.0.17108.20000",
    "Channel": "BetaChannel",
    "Name": "Beta",
    "Date": "2023-11-14T17:52:06.073Z",
    "URI": "https://officecdn.microsoft.com/pr/wsus/setup.exe"
  },
  {
    "Version": "16.0.17029.20028",
    "Channel": "CurrentPreview",
    "Name": "Current Channel (Preview)",
    "Date": "2023-11-13T16:27:54.627Z",
    "URI": "https://officecdn.microsoft.com/pr/wsus/setup.exe"
  },
  {
    "Version": "16.0.16924.20150",
    "Channel": "Current",
    "Name": "Current Channel",
    "Date": "2023-11-14T08:48:00.043Z",
    "URI": "https://officecdn.microsoft.com/pr/wsus/setup.exe"
  },
  {
    "Version": "16.0.16827.20278",
    "Channel": "MonthlyEnterprise",
    "Name": "Monthly Enterprise",
    "Date": "2023-11-14T08:36:46.417Z",
    "URI": "https://officecdn.microsoft.com/pr/wsus/setup.exe"
  },
  {
    "Version": "16.0.16731.20398",
    "Channel": "SemiAnnualPreview",
    "Name": "Semi-Annual Channel Preview",
    "Date": "2023-11-14T09:38:24.547Z",
    "URI": "https://officecdn.microsoft.com/pr/wsus/setup.exe"
  },
  {
    "Version": "16.0.16130.20846",
    "Channel": "SemiAnnual",
    "Name": "Semi-Annual Channel",
    "Date": "2023-11-14T09:15:18.743Z",
    "URI": "https://officecdn.microsoft.com/pr/wsus/setup.exe"
  },
  {
    "Version": "16.0.14332.20604",
    "Channel": "PerpetualVL2021",
    "Name": "Office LTSC 2021 Perpetual Enterprise",
    "Date": "2023-11-14T14:19:24.803Z",
    "URI": "https://officecdn.microsoft.com/pr/wsus/setup.exe"
  },
  {
    "Version": "16.0.10404.20013",
    "Channel": "PerpetualVL2019",
    "Name": "Office 2019 Perpetual Enterprise",
    "Date": "2023-11-14T14:21:37.827Z",
    "URI": "https://officecdn.microsoft.com/pr/wsus/setup.exe"
  }
]