[
  {
    "Version": "2024.1.241101-alpha",
    "Architecture": "x64",
    "Release": "Alpha",
    "Date": "2024-01-24T11:13:59.172Z",
    "Size": 311111880,
    "Sha512": "uY7sfZpKQgk8ltkEq3wkWmzfU3o7JF4yWTTdhoIZIxuRdXfqHd0iDbIPuwfggbAJ5WV0lvfKILO9TWHT42oR4w==",
    "URI": "https://downloads.k8slens.dev/ide/Lens%20Setup%202024.1.241101-alpha.exe"
  },
  {
    "Version": "2024.1.170738-latest",
    "Architecture": "x64",
    "Release": "Stable",
    "Date": "2024-01-17T07:48:03.637Z",
    "Size": 302342056,
    "Sha512": "5/+BwOnZp5cc87i0Td5m+y/b75+dhWtShPxCZFCd06O5vxBaFiOdeTkFRvvF06+xb9FebiMBtwy/fgesqsjq7Q==",
    "URI": "https://downloads.k8slens.dev/ide/Lens%20Setup%202024.1.170738-latest.exe"
  }
]