[
  {
    "Version": "21.4.0",
    "Architecture": "ARM64",
    "Type": "msi",
    "Channel": "Current",
    "URI": "https://nodejs.org/dist/v21.4.0/node-v21.4.0-arm64.msi"
  },
  {
    "Version": "21.4.0",
    "Architecture": "x64",
    "Type": "msi",
    "Channel": "Current",
    "URI": "https://nodejs.org/dist/v21.4.0/node-v21.4.0-x64.msi"
  },
  {
    "Version": "21.4.0",
    "Architecture": "x86",
    "Type": "msi",
    "Channel": "Current",
    "URI": "https://nodejs.org/dist/v21.4.0/node-v21.4.0-x86.msi"
  },
  {
    "Version": "21.4.0",
    "Architecture": "ARM64",
    "Type": "zip",
    "Channel": "Current",
    "URI": "https://nodejs.org/dist/v21.4.0/node-v21.4.0-win-arm64.zip"
  },
  {
    "Version": "21.4.0",
    "Architecture": "x64",
    "Type": "zip",
    "Channel": "Current",
    "URI": "https://nodejs.org/dist/v21.4.0/node-v21.4.0-win-x64.zip"
  },
  {
    "Version": "21.4.0",
    "Architecture": "x86",
    "Type": "zip",
    "Channel": "Current",
    "URI": "https://nodejs.org/dist/v21.4.0/node-v21.4.0-win-x86.zip"
  },
  {
    "Version": "20.10.0",
    "Architecture": "x64",
    "Type": "msi",
    "Channel": "LTS",
    "URI": "https://nodejs.org/dist/v20.10.0/node-v20.10.0-x64.msi"
  },
  {
    "Version": "20.10.0",
    "Architecture": "x86",
    "Type": "msi",
    "Channel": "LTS",
    "URI": "https://nodejs.org/dist/v20.10.0/node-v20.10.0-x86.msi"
  },
  {
    "Version": "20.10.0",
    "Architecture": "x64",
    "Type": "zip",
    "Channel": "LTS",
    "URI": "https://nodejs.org/dist/v20.10.0/node-v20.10.0-win-x64.zip"
  },
  {
    "Version": "20.10.0",
    "Architecture": "x86",
    "Type": "zip",
    "Channel": "LTS",
    "URI": "https://nodejs.org/dist/v20.10.0/node-v20.10.0-win-x86.zip"
  }
]