[
  {
    "Version": "7.5.363",
    "Date": "30/10/2020",
    "Size": 5850944,
    "Sha256": null,
    "Architecture": "x64",
    "InstallerType": "Default",
    "Type": "exe",
    "URI": "https://github.com/toggl-open-source/toggldesktop/releases/download/v7.5.363/TogglDesktopInstaller-x64-7.5.363.exe"
  },
  {
    "Version": "7.5.363",
    "Date": "30/10/2020",
    "Size": 5449608,
    "Sha256": null,
    "Architecture": "x86",
    "InstallerType": "Default",
    "Type": "exe",
    "URI": "https://github.com/toggl-open-source/toggldesktop/releases/download/v7.5.363/TogglDesktopInstaller-7.5.363.exe"
  }
]